{"GlobalPropertiesHash":"WmC7zoH31kZahSUyhcUTMPNecWveKEbvu8PZuNKYjlQ=","FingerprintPatternsHash":"gq3WsqcKBUGTSNle7RKKyXRIwh7M8ccEqOqYvIzoM04=","PropertyOverridesHash":"8ZRc1sGeVrPBx4lD717BgRaQekyh78QKV9SKsdt638U=","InputHashes":["RI3XnxY7lZMx7g/TtpPTD90Q7d3j\u002B/iLDPc8lO2za1M=","ZMNNSYfVyW9453vjBYi7J7flbigpzyge6Tl2YNKaMKs=","H7RVS5zzUYhyWmGAuyLwERzPRUtQRWV74dZVttwQBsw="],"CachedAssets":{"RI3XnxY7lZMx7g/TtpPTD90Q7d3j\u002B/iLDPc8lO2za1M=":{"Identity":"C:\\Users\\User\\Desktop\\WarehouseAPI\\wwwroot\\index.html","SourceId":"WarehouseAPI","SourceType":"Discovered","ContentRoot":"C:\\Users\\User\\Desktop\\WarehouseAPI\\wwwroot\\","BasePath":"/","RelativePath":"index#[.{fingerprint}]?.html","AssetKind":"All","AssetMode":"All","AssetRole":"Primary","AssetMergeBehavior":null,"AssetMergeSource":"","RelatedAsset":null,"AssetTraitName":null,"AssetTraitValue":null,"Fingerprint":"gni3defmgf","Integrity":"LBb8Rw\u002BmE/JJXs6dkkKqILCvXHL/aSImOPWYegplzG8=","CopyToOutputDirectory":"Never","CopyToPublishDirectory":"PreserveNewest","OriginalItemSpec":"wwwroot\\index.html","FileLength":46930,"LastWriteTime":"2026-05-02T16:21:15.8252059+00:00"}},"CachedCopyCandidates":{}}